my_code.py
docker_update_exam-0.1.dist-info/METADATA
docker_update_exam-0.1.dist-info/WHEEL
docker_update_exam-0.1.dist-info/top_level.txt
docker_update_exam-0.1.dist-info/RECORD
