Metadata-Version: 2.4
Name: docker_update_exam
Version: 0.1
Summary: Моя крутая библиотека
Author: Твоё Имя
Requires-Python: >=3.6
Dynamic: author
Dynamic: requires-python
Dynamic: summary
